{"numFailedTestSuites":0,"numFailedTests":0,"numPassedTestSuites":15,"numPassedTests":15,"numPendingTestSuites":0,"numPendingTests":0,"numRuntimeErrorTestSuites":0,"numTodoTests":0,"numTotalTestSuites":15,"numTotalTests":15,"openHandles":[],"snapshot":{"added":0,"didUpdate":false,"failure":false,"filesAdded":0,"filesRemoved":0,"filesUnmatched":0,"filesUpdated":0,"matched":0,"total":0,"unchecked":0,"uncheckedKeysByFile":[],"unmatched":0,"updated":0},"startTime":1560899596463,"success":true,"testResults":[{"assertionResults":[{"ancestorTitles":[],"failureMessages":[],"fullName":"renders without crashing","location":null,"status":"passed","title":"renders without crashing"}],"endTime":1560899598692,"message":"","name":"/home/tasso/Projetos/RocketChat/Rocket.Chat.Livechat.Admin/packages/fuselage/src/components/SideBar/Menu/spec.js","startTime":1560899597797,"status":"passed","summary":""},{"assertionResults":[{"ancestorTitles":[],"failureMessages":[],"fullName":"renders without crashing","location":null,"status":"passed","title":"renders without crashing"}],"endTime":1560899598698,"message":"","name":"/home/tasso/Projetos/RocketChat/Rocket.Chat.Livechat.Admin/packages/fuselage/src/components/SideBar/MenuItem/spec.js","startTime":1560899597772,"status":"passed","summary":""},{"assertionResults":[{"ancestorTitles":[],"failureMessages":[],"fullName":"renders without crashing","location":null,"status":"passed","title":"renders without crashing"}],"endTime":1560899598708,"message":"","name":"/home/tasso/Projetos/RocketChat/Rocket.Chat.Livechat.Admin/packages/fuselage/src/components/Drawer/spec.js","startTime":1560899597798,"status":"passed","summary":""},{"assertionResults":[{"ancestorTitles":[],"failureMessages":[],"fullName":"renders without crashing","location":null,"status":"passed","title":"renders without crashing"}],"endTime":1560899598714,"message":"","name":"/home/tasso/Projetos/RocketChat/Rocket.Chat.Livechat.Admin/packages/fuselage/src/components/TextInput/spec.js","startTime":1560899597790,"status":"passed","summary":""},{"assertionResults":[{"ancestorTitles":[],"failureMessages":[],"fullName":"renders without crashing","location":null,"status":"passed","title":"renders without crashing"}],"endTime":1560899598736,"message":"","name":"/home/tasso/Projetos/RocketChat/Rocket.Chat.Livechat.Admin/packages/fuselage/src/components/ScrollableArea/spec.js","startTime":1560899597777,"status":"passed","summary":""},{"assertionResults":[{"ancestorTitles":[],"failureMessages":[],"fullName":"renders without crashing","location":null,"status":"passed","title":"renders without crashing"}],"endTime":1560899598749,"message":"","name":"/home/tasso/Projetos/RocketChat/Rocket.Chat.Livechat.Admin/packages/fuselage/src/components/PageHeader/spec.js","startTime":1560899597787,"status":"passed","summary":""},{"assertionResults":[{"ancestorTitles":[],"failureMessages":[],"fullName":"renders without crashing","location":null,"status":"passed","title":"renders without crashing"}],"endTime":1560899598753,"message":"","name":"/home/tasso/Projetos/RocketChat/Rocket.Chat.Livechat.Admin/packages/fuselage/src/components/SideBar/Header/spec.js","startTime":1560899597790,"status":"passed","summary":""},{"assertionResults":[{"ancestorTitles":[],"failureMessages":[],"fullName":"renders without crashing","location":null,"status":"passed","title":"renders without crashing"}],"endTime":1560899598947,"message":"","name":"/home/tasso/Projetos/RocketChat/Rocket.Chat.Livechat.Admin/packages/fuselage/src/components/ButtonGroup/spec.js","startTime":1560899598778,"status":"passed","summary":""},{"assertionResults":[{"ancestorTitles":[],"failureMessages":[],"fullName":"renders without crashing","location":null,"status":"passed","title":"renders without crashing"}],"endTime":1560899598960,"message":"","name":"/home/tasso/Projetos/RocketChat/Rocket.Chat.Livechat.Admin/packages/fuselage/src/components/SideBar/spec.js","startTime":1560899598820,"status":"passed","summary":""},{"assertionResults":[{"ancestorTitles":[],"failureMessages":[],"fullName":"renders without crashing","location":null,"status":"passed","title":"renders without crashing"}],"endTime":1560899598997,"message":"","name":"/home/tasso/Projetos/RocketChat/Rocket.Chat.Livechat.Admin/packages/fuselage/src/components/Tabs/spec.js","startTime":1560899598829,"status":"passed","summary":""},{"assertionResults":[{"ancestorTitles":[],"failureMessages":[],"fullName":"renders without crashing","location":null,"status":"passed","title":"renders without crashing"}],"endTime":1560899598999,"message":"","name":"/home/tasso/Projetos/RocketChat/Rocket.Chat.Livechat.Admin/packages/fuselage/src/components/Button/spec.js","startTime":1560899598834,"status":"passed","summary":""},{"assertionResults":[{"ancestorTitles":[],"failureMessages":[],"fullName":"renders without crashing","location":null,"status":"passed","title":"renders without crashing"}],"endTime":1560899599004,"message":"","name":"/home/tasso/Projetos/RocketChat/Rocket.Chat.Livechat.Admin/packages/fuselage/src/components/Grid/spec.js","startTime":1560899598836,"status":"passed","summary":""},{"assertionResults":[{"ancestorTitles":[],"failureMessages":[],"fullName":"renders without crashing","location":null,"status":"passed","title":"renders without crashing"}],"endTime":1560899599005,"message":"","name":"/home/tasso/Projetos/RocketChat/Rocket.Chat.Livechat.Admin/packages/fuselage/src/components/CheckBox/spec.js","startTime":1560899598803,"status":"passed","summary":""},{"assertionResults":[{"ancestorTitles":[],"failureMessages":[],"fullName":"renders without crashing","location":null,"status":"passed","title":"renders without crashing"}],"endTime":1560899599007,"message":"","name":"/home/tasso/Projetos/RocketChat/Rocket.Chat.Livechat.Admin/packages/fuselage/src/components/Icon/spec.js","startTime":1560899598821,"status":"passed","summary":""},{"assertionResults":[{"ancestorTitles":[],"failureMessages":[],"fullName":"renders without crashing","location":null,"status":"passed","title":"renders without crashing"}],"endTime":1560899599084,"message":"","name":"/home/tasso/Projetos/RocketChat/Rocket.Chat.Livechat.Admin/packages/fuselage/src/components/Tab/spec.js","startTime":1560899598961,"status":"passed","summary":""}],"wasInterrupted":false}