{"numFailedTestSuites":0,"numFailedTests":0,"numPassedTestSuites":25,"numPassedTests":30,"numPendingTestSuites":0,"numPendingTests":0,"numRuntimeErrorTestSuites":0,"numTodoTests":0,"numTotalTestSuites":25,"numTotalTests":30,"openHandles":[],"snapshot":{"added":0,"didUpdate":false,"failure":false,"filesAdded":0,"filesRemoved":0,"filesRemovedList":[],"filesUnmatched":0,"filesUpdated":0,"matched":0,"total":0,"unchecked":0,"uncheckedKeysByFile":[],"unmatched":0,"updated":0},"startTime":1570954923936,"success":true,"testResults":[{"assertionResults":[{"ancestorTitles":[],"failureMessages":[],"fullName":"renders without crashing","location":null,"status":"passed","title":"renders without crashing"},{"ancestorTitles":["Skeleton"],"failureMessages":[],"fullName":"Skeleton renders without crashing","location":null,"status":"passed","title":"renders without crashing"}],"endTime":1570954927781,"message":"","name":"/Users/tasso/Projetos/Rocket.Chat.Fuselage/packages/fuselage/src/components/Subtitle/spec.js","startTime":1570954925771,"status":"passed","summary":""},{"assertionResults":[{"ancestorTitles":[],"failureMessages":[],"fullName":"renders without crashing","location":null,"status":"passed","title":"renders without crashing"},{"ancestorTitles":["Skeleton"],"failureMessages":[],"fullName":"Skeleton renders without crashing","location":null,"status":"passed","title":"renders without crashing"}],"endTime":1570954927853,"message":"","name":"/Users/tasso/Projetos/Rocket.Chat.Fuselage/packages/fuselage/src/components/InputBox/spec.js","startTime":1570954925798,"status":"passed","summary":""},{"assertionResults":[{"ancestorTitles":[],"failureMessages":[],"fullName":"renders without crashing","location":null,"status":"passed","title":"renders without crashing"},{"ancestorTitles":["Skeleton"],"failureMessages":[],"fullName":"Skeleton renders without crashing","location":null,"status":"passed","title":"renders without crashing"}],"endTime":1570954927906,"message":"","name":"/Users/tasso/Projetos/Rocket.Chat.Fuselage/packages/fuselage/src/components/Paragraph/spec.js","startTime":1570954925806,"status":"passed","summary":""},{"assertionResults":[{"ancestorTitles":[],"failureMessages":[],"fullName":"renders without crashing","location":null,"status":"passed","title":"renders without crashing"}],"endTime":1570954927985,"message":"","name":"/Users/tasso/Projetos/Rocket.Chat.Fuselage/packages/fuselage/src/components/TextAreaInput/spec.js","startTime":1570954925828,"status":"passed","summary":""},{"assertionResults":[{"ancestorTitles":[],"failureMessages":[],"fullName":"renders without crashing","location":null,"status":"passed","title":"renders without crashing"},{"ancestorTitles":["Skeleton"],"failureMessages":[],"fullName":"Skeleton renders without crashing","location":null,"status":"passed","title":"renders without crashing"}],"endTime":1570954927993,"message":"","name":"/Users/tasso/Projetos/Rocket.Chat.Fuselage/packages/fuselage/src/components/Headline/spec.js","startTime":1570954925883,"status":"passed","summary":""},{"assertionResults":[{"ancestorTitles":[],"failureMessages":[],"fullName":"renders without crashing","location":null,"status":"passed","title":"renders without crashing"}],"endTime":1570954927993,"message":"","name":"/Users/tasso/Projetos/Rocket.Chat.Fuselage/packages/fuselage/src/components/TelephoneInput/spec.js","startTime":1570954925805,"status":"passed","summary":""},{"assertionResults":[{"ancestorTitles":[],"failureMessages":[],"fullName":"renders without crashing","location":null,"status":"passed","title":"renders without crashing"},{"ancestorTitles":["Skeleton"],"failureMessages":[],"fullName":"Skeleton renders without crashing","location":null,"status":"passed","title":"renders without crashing"}],"endTime":1570954928054,"message":"","name":"/Users/tasso/Projetos/Rocket.Chat.Fuselage/packages/fuselage/src/components/Text/spec.js","startTime":1570954925911,"status":"passed","summary":""},{"assertionResults":[{"ancestorTitles":[],"failureMessages":[],"fullName":"renders without crashing","location":null,"status":"passed","title":"renders without crashing"}],"endTime":1570954928296,"message":"","name":"/Users/tasso/Projetos/Rocket.Chat.Fuselage/packages/fuselage/src/components/Hint/spec.js","startTime":1570954927835,"status":"passed","summary":""},{"assertionResults":[{"ancestorTitles":[],"failureMessages":[],"fullName":"renders without crashing","location":null,"status":"passed","title":"renders without crashing"}],"endTime":1570954928340,"message":"","name":"/Users/tasso/Projetos/Rocket.Chat.Fuselage/packages/fuselage/src/components/SelectInput/spec.js","startTime":1570954927895,"status":"passed","summary":""},{"assertionResults":[{"ancestorTitles":[],"failureMessages":[],"fullName":"renders without crashing","location":null,"status":"passed","title":"renders without crashing"}],"endTime":1570954928427,"message":"","name":"/Users/tasso/Projetos/Rocket.Chat.Fuselage/packages/fuselage/src/components/CheckBox/spec.js","startTime":1570954928089,"status":"passed","summary":""},{"assertionResults":[{"ancestorTitles":[],"failureMessages":[],"fullName":"renders without crashing","location":null,"status":"passed","title":"renders without crashing"}],"endTime":1570954928459,"message":"","name":"/Users/tasso/Projetos/Rocket.Chat.Fuselage/packages/fuselage/src/components/EmailInput/spec.js","startTime":1570954928062,"status":"passed","summary":""},{"assertionResults":[{"ancestorTitles":[],"failureMessages":[],"fullName":"renders without crashing","location":null,"status":"passed","title":"renders without crashing"}],"endTime":1570954928476,"message":"","name":"/Users/tasso/Projetos/Rocket.Chat.Fuselage/packages/fuselage/src/components/Button/spec.js","startTime":1570954928113,"status":"passed","summary":""},{"assertionResults":[{"ancestorTitles":[],"failureMessages":[],"fullName":"renders without crashing","location":null,"status":"passed","title":"renders without crashing"}],"endTime":1570954928494,"message":"","name":"/Users/tasso/Projetos/Rocket.Chat.Fuselage/packages/fuselage/src/components/PasswordInput/spec.js","startTime":1570954927926,"status":"passed","summary":""},{"assertionResults":[{"ancestorTitles":[],"failureMessages":[],"fullName":"renders without crashing","location":null,"status":"passed","title":"renders without crashing"}],"endTime":1570954928574,"message":"","name":"/Users/tasso/Projetos/Rocket.Chat.Fuselage/packages/fuselage/src/components/UrlInput/spec.js","startTime":1570954928048,"status":"passed","summary":""},{"assertionResults":[{"ancestorTitles":[],"failureMessages":[],"fullName":"renders without crashing","location":null,"status":"passed","title":"renders without crashing"}],"endTime":1570954928718,"message":"","name":"/Users/tasso/Projetos/Rocket.Chat.Fuselage/packages/fuselage/src/components/InputControl/spec.js","startTime":1570954928304,"status":"passed","summary":""},{"assertionResults":[{"ancestorTitles":[],"failureMessages":[],"fullName":"renders without crashing","location":null,"status":"passed","title":"renders without crashing"}],"endTime":1570954928726,"message":"","name":"/Users/tasso/Projetos/Rocket.Chat.Fuselage/packages/fuselage/src/components/Label/spec.js","startTime":1570954928349,"status":"passed","summary":""},{"assertionResults":[{"ancestorTitles":[],"failureMessages":[],"fullName":"renders without crashing","location":null,"status":"passed","title":"renders without crashing"}],"endTime":1570954928806,"message":"","name":"/Users/tasso/Projetos/Rocket.Chat.Fuselage/packages/fuselage/src/components/Icon/spec.js","startTime":1570954928468,"status":"passed","summary":""},{"assertionResults":[{"ancestorTitles":[],"failureMessages":[],"fullName":"renders without crashing","location":null,"status":"passed","title":"renders without crashing"}],"endTime":1570954928809,"message":"","name":"/Users/tasso/Projetos/Rocket.Chat.Fuselage/packages/fuselage/src/components/ToggleSwitch/spec.js","startTime":1570954928435,"status":"passed","summary":""},{"assertionResults":[{"ancestorTitles":[],"failureMessages":[],"fullName":"renders without crashing","location":null,"status":"passed","title":"renders without crashing"}],"endTime":1570954928829,"message":"","name":"/Users/tasso/Projetos/Rocket.Chat.Fuselage/packages/fuselage/src/components/ButtonGroup/spec.js","startTime":1570954928512,"status":"passed","summary":""},{"assertionResults":[{"ancestorTitles":[],"failureMessages":[],"fullName":"renders without crashing","location":null,"status":"passed","title":"renders without crashing"}],"endTime":1570954928868,"message":"","name":"/Users/tasso/Projetos/Rocket.Chat.Fuselage/packages/fuselage/src/components/Field/spec.js","startTime":1570954928491,"status":"passed","summary":""},{"assertionResults":[{"ancestorTitles":[],"failureMessages":[],"fullName":"renders without crashing","location":null,"status":"passed","title":"renders without crashing"}],"endTime":1570954928930,"message":"","name":"/Users/tasso/Projetos/Rocket.Chat.Fuselage/packages/fuselage/src/components/Box/spec.js","startTime":1570954928596,"status":"passed","summary":""},{"assertionResults":[{"ancestorTitles":[],"failureMessages":[],"fullName":"renders without crashing","location":null,"status":"passed","title":"renders without crashing"}],"endTime":1570954929054,"message":"","name":"/Users/tasso/Projetos/Rocket.Chat.Fuselage/packages/fuselage/src/components/FieldGroup/spec.js","startTime":1570954928753,"status":"passed","summary":""},{"assertionResults":[{"ancestorTitles":[],"failureMessages":[],"fullName":"renders without crashing","location":null,"status":"passed","title":"renders without crashing"}],"endTime":1570954929062,"message":"","name":"/Users/tasso/Projetos/Rocket.Chat.Fuselage/packages/fuselage/src/components/SearchInput/spec.js","startTime":1570954928727,"status":"passed","summary":""},{"assertionResults":[{"ancestorTitles":[],"failureMessages":[],"fullName":"renders without crashing","location":null,"status":"passed","title":"renders without crashing"}],"endTime":1570954929099,"message":"","name":"/Users/tasso/Projetos/Rocket.Chat.Fuselage/packages/fuselage/src/components/RadioButton/spec.js","startTime":1570954928838,"status":"passed","summary":""},{"assertionResults":[{"ancestorTitles":[],"failureMessages":[],"fullName":"renders without crashing","location":null,"status":"passed","title":"renders without crashing"}],"endTime":1570954929134,"message":"","name":"/Users/tasso/Projetos/Rocket.Chat.Fuselage/packages/fuselage/src/components/TextInput/spec.js","startTime":1570954928818,"status":"passed","summary":""}],"wasInterrupted":false}