{"numFailedTestSuites":0,"numFailedTests":0,"numPassedTestSuites":18,"numPassedTests":18,"numPendingTestSuites":0,"numPendingTests":0,"numRuntimeErrorTestSuites":0,"numTodoTests":0,"numTotalTestSuites":18,"numTotalTests":18,"openHandles":[],"snapshot":{"added":0,"didUpdate":false,"failure":false,"filesAdded":0,"filesRemoved":0,"filesUnmatched":0,"filesUpdated":0,"matched":0,"total":0,"unchecked":0,"uncheckedKeysByFile":[],"unmatched":0,"updated":0},"startTime":1562036079441,"success":true,"testResults":[{"assertionResults":[{"ancestorTitles":[],"failureMessages":[],"fullName":"renders without crashing","location":null,"status":"passed","title":"renders without crashing"}],"endTime":1562036081900,"message":"","name":"/home/tasso/Projetos/RocketChat/Rocket.Chat.Livechat.Admin/packages/fuselage/src/components/SideBar/Header/spec.js","startTime":1562036080752,"status":"passed","summary":""},{"assertionResults":[{"ancestorTitles":[],"failureMessages":[],"fullName":"renders without crashing","location":null,"status":"passed","title":"renders without crashing"}],"endTime":1562036081901,"message":"","name":"/home/tasso/Projetos/RocketChat/Rocket.Chat.Livechat.Admin/packages/fuselage/src/components/ButtonGroup/spec.js","startTime":1562036080785,"status":"passed","summary":""},{"assertionResults":[{"ancestorTitles":[],"failureMessages":[],"fullName":"renders without crashing","location":null,"status":"passed","title":"renders without crashing"}],"endTime":1562036081908,"message":"","name":"/home/tasso/Projetos/RocketChat/Rocket.Chat.Livechat.Admin/packages/fuselage/src/components/Page/Header/spec.js","startTime":1562036080781,"status":"passed","summary":""},{"assertionResults":[{"ancestorTitles":[],"failureMessages":[],"fullName":"renders without crashing","location":null,"status":"passed","title":"renders without crashing"}],"endTime":1562036081916,"message":"","name":"/home/tasso/Projetos/RocketChat/Rocket.Chat.Livechat.Admin/packages/fuselage/src/components/ScrollableArea/spec.js","startTime":1562036080822,"status":"passed","summary":""},{"assertionResults":[{"ancestorTitles":[],"failureMessages":[],"fullName":"renders without crashing","location":null,"status":"passed","title":"renders without crashing"}],"endTime":1562036081926,"message":"","name":"/home/tasso/Projetos/RocketChat/Rocket.Chat.Livechat.Admin/packages/fuselage/src/components/SideBar/Menu/spec.js","startTime":1562036080695,"status":"passed","summary":""},{"assertionResults":[{"ancestorTitles":[],"failureMessages":[],"fullName":"renders without crashing","location":null,"status":"passed","title":"renders without crashing"}],"endTime":1562036081940,"message":"","name":"/home/tasso/Projetos/RocketChat/Rocket.Chat.Livechat.Admin/packages/fuselage/src/components/Drawer/spec.js","startTime":1562036080727,"status":"passed","summary":""},{"assertionResults":[{"ancestorTitles":[],"failureMessages":[],"fullName":"renders without crashing","location":null,"status":"passed","title":"renders without crashing"}],"endTime":1562036081953,"message":"","name":"/home/tasso/Projetos/RocketChat/Rocket.Chat.Livechat.Admin/packages/fuselage/src/components/SideBar/MenuItem/spec.js","startTime":1562036080780,"status":"passed","summary":""},{"assertionResults":[{"ancestorTitles":[],"failureMessages":[],"fullName":"renders without crashing","location":null,"status":"passed","title":"renders without crashing"}],"endTime":1562036082145,"message":"","name":"/home/tasso/Projetos/RocketChat/Rocket.Chat.Livechat.Admin/packages/fuselage/src/components/Tabs/spec.js","startTime":1562036081959,"status":"passed","summary":""},{"assertionResults":[{"ancestorTitles":[],"failureMessages":[],"fullName":"renders without crashing","location":null,"status":"passed","title":"renders without crashing"}],"endTime":1562036082148,"message":"","name":"/home/tasso/Projetos/RocketChat/Rocket.Chat.Livechat.Admin/packages/fuselage/src/components/Form/spec.js","startTime":1562036081929,"status":"passed","summary":""},{"assertionResults":[{"ancestorTitles":[],"failureMessages":[],"fullName":"renders without crashing","location":null,"status":"passed","title":"renders without crashing"}],"endTime":1562036082155,"message":"","name":"/home/tasso/Projetos/RocketChat/Rocket.Chat.Livechat.Admin/packages/fuselage/src/components/Tab/spec.js","startTime":1562036081935,"status":"passed","summary":""},{"assertionResults":[{"ancestorTitles":[],"failureMessages":[],"fullName":"renders without crashing","location":null,"status":"passed","title":"renders without crashing"}],"endTime":1562036082158,"message":"","name":"/home/tasso/Projetos/RocketChat/Rocket.Chat.Livechat.Admin/packages/fuselage/src/components/SideBar/spec.js","startTime":1562036081945,"status":"passed","summary":""},{"assertionResults":[{"ancestorTitles":[],"failureMessages":[],"fullName":"renders without crashing","location":null,"status":"passed","title":"renders without crashing"}],"endTime":1562036082171,"message":"","name":"/home/tasso/Projetos/RocketChat/Rocket.Chat.Livechat.Admin/packages/fuselage/src/components/Page/spec.js","startTime":1562036081944,"status":"passed","summary":""},{"assertionResults":[{"ancestorTitles":[],"failureMessages":[],"fullName":"renders without crashing","location":null,"status":"passed","title":"renders without crashing"}],"endTime":1562036082177,"message":"","name":"/home/tasso/Projetos/RocketChat/Rocket.Chat.Livechat.Admin/packages/fuselage/src/components/Grid/spec.js","startTime":1562036081935,"status":"passed","summary":""},{"assertionResults":[{"ancestorTitles":[],"failureMessages":[],"fullName":"renders without crashing","location":null,"status":"passed","title":"renders without crashing"}],"endTime":1562036082221,"message":"","name":"/home/tasso/Projetos/RocketChat/Rocket.Chat.Livechat.Admin/packages/fuselage/src/components/CheckBox/spec.js","startTime":1562036081977,"status":"passed","summary":""},{"assertionResults":[{"ancestorTitles":[],"failureMessages":[],"fullName":"renders without crashing","location":null,"status":"passed","title":"renders without crashing"}],"endTime":1562036082303,"message":"","name":"/home/tasso/Projetos/RocketChat/Rocket.Chat.Livechat.Admin/packages/fuselage/src/components/TextInput/spec.js","startTime":1562036082163,"status":"passed","summary":""},{"assertionResults":[{"ancestorTitles":[],"failureMessages":[],"fullName":"renders without crashing","location":null,"status":"passed","title":"renders without crashing"}],"endTime":1562036082313,"message":"","name":"/home/tasso/Projetos/RocketChat/Rocket.Chat.Livechat.Admin/packages/fuselage/src/components/Icon/spec.js","startTime":1562036082166,"status":"passed","summary":""},{"assertionResults":[{"ancestorTitles":[],"failureMessages":[],"fullName":"renders without crashing","location":null,"status":"passed","title":"renders without crashing"}],"endTime":1562036082322,"message":"","name":"/home/tasso/Projetos/RocketChat/Rocket.Chat.Livechat.Admin/packages/fuselage/src/components/Button/spec.js","startTime":1562036082174,"status":"passed","summary":""},{"assertionResults":[{"ancestorTitles":[],"failureMessages":[],"fullName":"renders without crashing","location":null,"status":"passed","title":"renders without crashing"}],"endTime":1562036082622,"message":"","name":"/home/tasso/Projetos/RocketChat/Rocket.Chat.Livechat.Admin/packages/fuselage/src/components/Form/Field/spec.js","startTime":1562036082178,"status":"passed","summary":""}],"wasInterrupted":false}